pyfitsserver/__init__.py
pyfitsserver/__main__.py
pyfitsserver/server.py
pyfitsserver/template.html
pyfitsserver/data/aia_171_test_img.fits
pyfitsserver/lib/__init__.py
pyfitsserver/lib/color_tables.py
pyfitsserver/lib/idl_3.csv
pyfitsserver/lib/install_pyfitsVSC.py
pyfitsserver/lib/ping_previewer.py
pyfitsserver/lib/start_server.sh
pyfitsserver/lib/stop_server.sh
pyfitsserver-0.0.29.dist-info/LICENSE
pyfitsserver-0.0.29.dist-info/METADATA
pyfitsserver-0.0.29.dist-info/WHEEL
pyfitsserver-0.0.29.dist-info/entry_points.txt
pyfitsserver-0.0.29.dist-info/top_level.txt
pyfitsserver-0.0.29.dist-info/RECORD
