Metadata-Version: 2.1
Name: pyfitsserver
Version: 0.0.29
Summary: A lightweight server to facilitate the rendering and previewing of FITS files.
Home-page: https://github.com/GillySpace27/pyFitsServer
Author: Gilly
Author-email: Gilly <gilly@swri.org>
License: MIT License
Project-URL: Home, https://github.com/GillySpace27/pyFitsServer
Keywords: FITS,Astrophysics,Server,Flask
Classifier: Development Status :: 3 - Alpha
Classifier: Intended Audience :: Developers
Classifier: License :: OSI Approved :: MIT License
Classifier: Programming Language :: Python :: 3
Requires-Python: >=3.8
License-File: LICENSE
Requires-Dist: Flask[async]<3.0,>=2.0
Requires-Dist: numpy
Requires-Dist: astropy
Requires-Dist: matplotlib
Requires-Dist: parse
Requires-Dist: Pillow
Requires-Dist: requests
Requires-Dist: scipy
Requires-Dist: Werkzeug==2.2.2
Provides-Extra: dev
Requires-Dist: setuptools>=42; extra == "dev"
Requires-Dist: wheel; extra == "dev"
